cligraphy/__init__.py
cligraphy/core/__init__.py
cligraphy/core/cli.py
cligraphy/core/decorators.py
cligraphy/core/log.py
cligraphy/core/parsers.py
cligraphy/core/reporting.py
cligraphy/core/tracking.py
cligraphy/core/util.py
cligraphy/core/capture/__init__.py
cligraphy/core/capture/fmt_capnp.py
cligraphy/core/capture/ptysnoop.py
cligraphy/core/capture/termsize.py
cligraphy/core/lib/__init__.py
cligraphy/core/lib/cli_ui.py
cligraphy/core/lib/ssh.py
cligraphy/core/lib/times.py
cligraphy-0.1.1.dist-info/METADATA
cligraphy-0.1.1.dist-info/WHEEL
cligraphy-0.1.1.dist-info/top_level.txt
cligraphy-0.1.1.dist-info/RECORD
